arguments.py
main.py
models.py
project.py
backbones/__init__.py
backbones/apnrru.py
backbones/bojanet.py
backbones/deltagru.py
backbones/deltagru_tcnskip.py
backbones/deltajanet.py
backbones/dgru.py
backbones/dvrjanet.py
backbones/gmp.py
backbones/gru.py
backbones/lstm.py
backbones/mcldnn.py
backbones/neuraltx.py
backbones/pgjanet.py
backbones/qgru.py
backbones/qgru_amp1.py
backbones/rvtdcnn.py
backbones/tcnn.py
backbones/vdlstm.py
datasets/__init__.py
datasets/APA_200MHz/spec.json
datasets/APA_200MHz/test_input.csv
datasets/APA_200MHz/test_output.csv
datasets/APA_200MHz/train_input.csv
datasets/APA_200MHz/train_output.csv
datasets/APA_200MHz/val_input.csv
datasets/APA_200MHz/val_output.csv
datasets/APA_200MHz_b/spec.json
datasets/APA_200MHz_b/test_input.csv
datasets/APA_200MHz_b/test_output.csv
datasets/APA_200MHz_b/train_input.csv
datasets/APA_200MHz_b/train_output.csv
datasets/APA_200MHz_b/val_input.csv
datasets/APA_200MHz_b/val_output.csv
datasets/DPA_100MHz/spec.json
datasets/DPA_100MHz/test_input.csv
datasets/DPA_100MHz/test_output.csv
datasets/DPA_100MHz/train_input.csv
datasets/DPA_100MHz/train_output.csv
datasets/DPA_100MHz/val_input.csv
datasets/DPA_100MHz/val_output.csv
datasets/DPA_160MHz/spec.json
datasets/DPA_160MHz/test_input.csv
datasets/DPA_160MHz/test_output.csv
datasets/DPA_160MHz/train_input.csv
datasets/DPA_160MHz/train_output.csv
datasets/DPA_160MHz/val_input.csv
datasets/DPA_160MHz/val_output.csv
datasets/DPA_200MHz/spec.json
datasets/DPA_200MHz/test_input.csv
datasets/DPA_200MHz/test_output.csv
datasets/DPA_200MHz/train_input.csv
datasets/DPA_200MHz/train_output.csv
datasets/DPA_200MHz/val_input.csv
datasets/DPA_200MHz/val_output.csv
datasets/MyCustomPA/data.csv
datasets/MyCustomPA/spec.json
modules/__init__.py
modules/data_collector.py
modules/loggers.py
modules/paths.py
modules/train_funcs.py
opendpd/__init__.py
opendpd/api.py
opendpd/cli.py
opendpd-2.0.0.dist-info/licenses/LICENSE
quant/__init__.py
quant/quant_envs.py
quant/modules/__init__.py
quant/modules/gru.py
opendpd-2.0.0.dist-info/METADATA
opendpd-2.0.0.dist-info/WHEEL
opendpd-2.0.0.dist-info/top_level.txt
opendpd-2.0.0.dist-info/RECORD
