Metadata-Version: 2.4
Name: opendpd
Version: 2.0.0
Summary: An end-to-end learning framework for modeling power amplifiers and digital pre-distortion
Home-page: https://github.com/yourusername/OpenDPD
Author: Chang Gao, Yizhuo Wu, Ang Li
Author-email: Chang Gao <chang.gao@tudelft.nl>, Yizhuo Wu <yizhuo.wu@tudelft.nl>, Ang Li <a.li-2@tudelft.nl>
Maintainer-email: Chang Gao <chang.gao@tudelft.nl>
License: Apache-2.0
Project-URL: Homepage, https://github.com/yourusername/OpenDPD
Project-URL: Documentation, https://github.com/yourusername/OpenDPD/blob/main/README.md
Project-URL: Repository, https://github.com/yourusername/OpenDPD
Project-URL: Issues, https://github.com/yourusername/OpenDPD/issues
Classifier: Development Status :: 4 - Beta
Classifier: Intended Audience :: Science/Research
Classifier: License :: OSI Approved :: Apache Software License
Classifier: Programming Language :: Python :: 3
Classifier: Programming Language :: Python :: 3.8
Classifier: Programming Language :: Python :: 3.9
Classifier: Programming Language :: Python :: 3.10
Classifier: Programming Language :: Python :: 3.11
Classifier: Programming Language :: Python :: 3.12
Classifier: Programming Language :: Python :: 3.13
Classifier: Topic :: Scientific/Engineering :: Artificial Intelligence
Requires-Python: >=3.8
License-File: LICENSE
Requires-Dist: torch>=2.4.0
Requires-Dist: numpy>=2.0.0
Requires-Dist: scipy>=1.7.0
Requires-Dist: pandas>=1.3.0
Requires-Dist: matplotlib>=3.4.0
Requires-Dist: tqdm>=4.62.0
Requires-Dist: rich>=10.0.0
Provides-Extra: dev
Requires-Dist: pytest>=6.0; extra == "dev"
Requires-Dist: pytest-cov>=2.0; extra == "dev"
Requires-Dist: black>=21.0; extra == "dev"
Requires-Dist: flake8>=3.9; extra == "dev"
Dynamic: author
Dynamic: home-page
Dynamic: license-file
Dynamic: requires-python
